{
  "$schema": "../gen/schemas/desktop-schema.json",
  "identifier": "default",
  "description": "Capability for the main window",
  "windows": ["main", "settings"],
  "permissions": [
    "core:default",
    "core:window:allow-start-dragging",
    "core:window:allow-hide",
    "core:window:allow-show",
    "core:window:allow-set-position",
    "core:window:allow-set-size",
    "core:window:allow-set-always-on-top",
    "core:window:allow-set-skip-taskbar",
    "core:window:allow-set-shadow",
    "core:window:allow-close",
    "opener:default",
    "shell:default",
    "shell:allow-execute",
    "fs:default",
    "fs:allow-read-file",
    "fs:allow-write-file",
    "fs:allow-read-dir",
    "fs:allow-create",
    "fs:allow-exists",
    "dialog:default",
    "dialog:allow-open",
    "dialog:allow-message"
  ]
}
